opencaselist/__init__.py
opencaselist/client.py
opencaselist/exceptions.py
opencaselist/models.py
opencaselist-0.2.0.dist-info/WHEEL
opencaselist-0.2.0.dist-info/METADATA
opencaselist-0.2.0.dist-info/RECORD
