Metadata-Version: 2.4
Name: opencaselist
Version: 0.2.0
Summary: Python client for opencaselist.com API
Author: Henry Beveridge
Author-email: Henry Beveridge <henrydbeveridge@gmail.com>
License-Expression: MIT
Classifier: Programming Language :: Python :: 3
Classifier: Intended Audience :: Developers
Classifier: License :: OSI Approved :: MIT License
Classifier: Operating System :: OS Independent
Requires-Dist: pydantic>=2.12.4
Requires-Dist: requests>=2.32.5
Requires-Python: >=3.13
Project-URL: Repository, https://github.com/illuminate-dev/opencaselist-python.git
